Workbook

Sheet Dashboard
A1: Personal Finance Dashboard
A3: Selected Month | B3: Aug 2026
A5: Total Income | C5: Total Expenses | E5: Net Cash Flow | G5: Budget Variance | I5: Savings | K5: Loan Payments
A6: =SUMIFS(Income!$F$4:$F$200,Income!$B$4:$B$200,$B$3,Income!$G$4:$G$200,"Received") -> 1700000 | C6: =SUMIFS(Expenses!$F$4:$F$500,Expenses!$B$4:$B$500,$B$3,Expenses!$H$4:$H$500,"Paid") -> 674000 | E6: =A6-C6 -> 1026000 | G6: =SUM(C11:C23)-SUM(B11:B23) -> 66000 | I6: =SUMIFS(Savings!$D$4:$D$200,Savings!$B$4:$B$200,$B$3,Savings!$F$4:$F$200,"Completed") -> 300000 | K6: =SUMIFS(Loans!$H$4:$H$200,Loans!$G$4:$G$200,$B$3,Loans!$I$4:$I$200,"Paid") -> 50000
A10: Expense Category | B10: Actual Spend | C10: Budget
A11: Rent | B11: =SUMIFS(Expenses!$F$4:$F$500,Expenses!$B$4:$B$500,$B$3,Expenses!$C$4:$C$500,A11,Expenses!$H$4:$H$500,"Paid") -> 100000 | C11: =SUMIFS(Budget!$B:$B,Budget!$A:$A,A11) -> 100000
A12: Electricity/Security | B12: =SUMIFS(Expenses!$F$4:$F$500,Expenses!$B$4:$B$500,$B$3,Expenses!$C$4:$C$500,A12,Expenses!$H$4:$H$500,"Paid") -> 22000 | C12: =SUMIFS(Budget!$B:$B,Budget!$A:$A,A12) -> 20000
A13: Internet/Airtime | B13: =SUMIFS(Expenses!$F$4:$F$500,Expenses!$B$4:$B$500,$B$3,Expenses!$C$4:$C$500,A13,Expenses!$H$4:$H$500,"Paid") -> 35000 | C13: =SUMIFS(Budget!$B:$B,Budget!$A:$A,A13) -> 35000
A14: Transport | B14: =SUMIFS(Expenses!$F$4:$F$500,Expenses!$B$4:$B$500,$B$3,Expenses!$C$4:$C$500,A14,Expenses!$H$4:$H$500,"Paid") -> 50000 | C14: =SUMIFS(Budget!$B:$B,Budget!$A:$A,A14) -> 50000
A15: Food | B15: =SUMIFS(Expenses!$F$4:$F$500,Expenses!$B$4:$B$500,$B$3,Expenses!$C$4:$C$500,A15,Expenses!$H$4:$H$500,"Paid") -> 105000 | C15: =SUMIFS(Budget!$B:$B,Budget!$A:$A,A15) -> 150000
A16: Personal Care | B16: =SUMIFS(Expenses!$F$4:$F$500,Expenses!$B$4:$B$500,$B$3,Expenses!$C$4:$C$500,A16,Expenses!$H$4:$H$500,"Paid") -> 45000 | C16: =SUMIFS(Budget!$B:$B,Budget!$A:$A,A16) -> 50000
A17: Healthcare | B17: =SUMIFS(Expenses!$F$4:$F$500,Expenses!$B$4:$B$500,$B$3,Expenses!$C$4:$C$500,A17,Expenses!$H$4:$H$500,"Paid") -> 30000 | C17: =SUMIFS(Budget!$B:$B,Budget!$A:$A,A17) -> 50000
A18: Family Support | B18: =SUMIFS(Expenses!$F$4:$F$500,Expenses!$B$4:$B$500,$B$3,Expenses!$C$4:$C$500,A18,Expenses!$H$4:$H$500,"Paid") -> 80000 | C18: =SUMIFS(Budget!$B:$B,Budget!$A:$A,A18) -> 80000
A19: Church Giving | B19: =SUMIFS(Expenses!$F$4:$F$500,Expenses!$B$4:$B$500,$B$3,Expenses!$C$4:$C$500,A19,Expenses!$H$4:$H$500,"Paid") -> 120000 | C19: =SUMIFS(Budget!$B:$B,Budget!$A:$A,A19) -> 120000
A20: Charity | B20: =SUMIFS(Expenses!$F$4:$F$500,Expenses!$B$4:$B$500,$B$3,Expenses!$C$4:$C$500,A20,Expenses!$H$4:$H$500,"Paid") -> 30000 | C20: =SUMIFS(Budget!$B:$B,Budget!$A:$A,A20) -> 30000
A21: Education | B21: =SUMIFS(Expenses!$F$4:$F$500,Expenses!$B$4:$B$500,$B$3,Expenses!$C$4:$C$500,A21,Expenses!$H$4:$H$500,"Paid") -> 25000 | C21: =SUMIFS(Budget!$B:$B,Budget!$A:$A,A21) -> 20000
A22: Travel | B22: =SUMIFS(Expenses!$F$4:$F$500,Expenses!$B$4:$B$500,$B$3,Expenses!$C$4:$C$500,A22,Expenses!$H$4:$H$500,"Paid") -> 17000 | C22: =SUMIFS(Budget!$B:$B,Budget!$A:$A,A22) -> 20000
A23: Miscellaneous | B23: =SUMIFS(Expenses!$F$4:$F$500,Expenses!$B$4:$B$500,$B$3,Expenses!$C$4:$C$500,A23,Expenses!$H$4:$H$500,"Paid") -> 15000 | C23: =SUMIFS(Budget!$B:$B,Budget!$A:$A,A23) -> 15000
A24: Total | B24: =SUM(B11:B23) -> 674000 | C24: =SUM(C11:C23) -> 740000
A26: Goal | B26: Target | C26: Saved | D26: Remaining
A27: =Goals!A4 -> Emergency Fund | B27: =Goals!B4 -> 4440000 | C27: =Goals!C4 -> 600000 | D27: =Goals!D4 -> 3840000
A28: =Goals!A5 -> Laptop Upgrade | B28: =Goals!B5 -> 700000 | C28: =Goals!C5 -> 0 | D28: =Goals!D5 -> 700000
A29: =Goals!A6 -> Training/Certification | B29: =Goals!B6 -> 300000 | C29: =Goals!C6 -> 0 | D29: =Goals!D6 -> 300000

Sheet Income
A1: Income Tracker
A3: Date | B3: Month | C3: Source | D3: Description | E3: Expected Date | F3: Amount | G3: Status | H3: Notes
A4: 46214 | B4: =IF(A4="","",TEXT(A4,"mmm yyyy")) -> Jul 2026 | C4: Salary | D4: Monthly salary | E4: 11th | F4: 1400000 | G4: Received | H4: Update status monthly
A5: 46245 | B5: =IF(A5="","",TEXT(A5,"mmm yyyy")) -> Aug 2026 | C5: Salary | D5: Monthly salary | E5: 11th | F5: 1400000 | G5: Received | H5: Update status monthly
A6: 46276 | B6: =IF(A6="","",TEXT(A6,"mmm yyyy")) -> Sep 2026 | C6: Salary | D6: Monthly salary | E6: 11th | F6: 1400000 | G6: Planned | H6: Update status monthly
A7: 46306 | B7: =IF(A7="","",TEXT(A7,"mmm yyyy")) -> Oct 2026 | C7: Salary | D7: Monthly salary | E7: 11th | F7: 1400000 | G7: Planned | H7: Update status monthly
A8: 46337 | B8: =IF(A8="","",TEXT(A8,"mmm yyyy")) -> Nov 2026 | C8: Salary | D8: Monthly salary | E8: 11th | F8: 1400000 | G8: Planned | H8: Update status monthly
A9: 46367 | B9: =IF(A9="","",TEXT(A9,"mmm yyyy")) -> Dec 2026 | C9: Salary | D9: Monthly salary | E9: 11th | F9: 1400000 | G9: Planned | H9: Update status monthly
A10: 46398 | B10: =IF(A10="","",TEXT(A10,"mmm yyyy")) -> Jan 2027 | C10: Salary | D10: Monthly salary | E10: 11th | F10: 1400000 | G10: Planned | H10: Update status monthly
A11: 46429 | B11: =IF(A11="","",TEXT(A11,"mmm yyyy")) -> Feb 2027 | C11: Salary | D11: Monthly salary | E11: 11th | F11: 1400000 | G11: Planned | H11: Update status monthly
A12: 46457 | B12: =IF(A12="","",TEXT(A12,"mmm yyyy")) -> Mar 2027 | C12: Salary | D12: Monthly salary | E12: 11th | F12: 1400000 | G12: Planned | H12: Update status monthly
A13: 46488 | B13: =IF(A13="","",TEXT(A13,"mmm yyyy")) -> Apr 2027 | C13: Salary | D13: Monthly salary | E13: 11th | F13: 1400000 | G13: Planned | H13: Update status monthly
A14: 46518 | B14: =IF(A14="","",TEXT(A14,"mmm yyyy")) -> May 2027 | C14: Salary | D14: Monthly salary | E14: 11th | F14: 1400000 | G14: Planned | H14: Update status monthly
A15: 46549 | B15: =IF(A15="","",TEXT(A15,"mmm yyyy")) -> Jun 2027 | C15: Salary | D15: Monthly salary | E15: 11th | F15: 1400000 | G15: Planned | H15: Update status monthly
... A17: 46249 | B17: =IF(A17="","",TEXT(A17,"mmm yyyy")) -> Aug 2026 | C17: Commission | D17: Monthly commission | E17: 15th | F17: 300000 | G17: Received | H17: Not guaranteed
A18: 46280 | B18: =IF(A18="","",TEXT(A18,"mmm yyyy")) -> Sep 2026 | C18: Commission | D18: Monthly commission | E18: 15th | G18: Planned | H18: Not guaranteed
B19: =IF(A19="","",TEXT(A19,"mmm yyyy"))
B20: =IF(A20="","",TEXT(A20,"mmm yyyy"))
B21: =IF(A21="","",TEXT(A21,"mmm yyyy"))
B22: =IF(A22="","",TEXT(A22,"mmm yyyy"))
B23: =IF(A23="","",TEXT(A23,"mmm yyyy"))
B24: =IF(A24="","",TEXT(A24,"mmm yyyy"))
B25: =IF(A25="","",TEXT(A25,"mmm yyyy"))
B26: =IF(A26="","",TEXT(A26,"mmm yyyy"))
B27: =IF(A27="","",TEXT(A27,"mmm yyyy"))
B28: =IF(A28="","",TEXT(A28,"mmm yyyy"))
B29: =IF(A29="","",TEXT(A29,"mmm yyyy"))
B30: =IF(A30="","",TEXT(A30,"mmm yyyy"))
... B200: =IF(A200="","",TEXT(A200,"mmm yyyy"))

Sheet Expenses
A1: Expense Tracker
A3: Date | B3: Month | C3: Category | D3: Subcategory | E3: Description | F3: Amount | G3: Payment Method | H3: Status | I3: Notes
A4: 46204 | B4: =IF(A4="","",TEXT(A4,"mmm yyyy")) -> Jul 2026 | C4: Rent | D4: Apartment | E4: Monthly rent | F4: 100000 | G4: Bank Transfer | H4: Paid
A5: 46206 | B5: =IF(A5="","",TEXT(A5,"mmm yyyy")) -> Jul 2026 | C5: Internet/Airtime | D5: Data | E5: Internet subscription | F5: 35000 | G5: Bank Transfer | H5: Paid
A6: 46208 | B6: =IF(A6="","",TEXT(A6,"mmm yyyy")) -> Jul 2026 | C6: Food | D6: Groceries | E6: Food and groceries | F6: 95000 | G6: Card | H6: Paid
A7: 46211 | B7: =IF(A7="","",TEXT(A7,"mmm yyyy")) -> Jul 2026 | C7: Transport | D7: Commute | E7: Transport | F7: 45000 | G7: Cash | H7: Paid
A8: 46213 | B8: =IF(A8="","",TEXT(A8,"mmm yyyy")) -> Jul 2026 | C8: Church Giving | D8: Tithe/Offering | E8: Church giving | F8: 120000 | G8: Bank Transfer | H8: Paid
A9: 46215 | B9: =IF(A9="","",TEXT(A9,"mmm yyyy")) -> Jul 2026 | C9: Family Support | D9: Family | E9: Family support | F9: 80000 | G9: Bank Transfer | H9: Paid
A10: 46218 | B10: =IF(A10="","",TEXT(A10,"mmm yyyy")) -> Jul 2026 | C10: Electricity/Security | D10: Utilities | E10: Electricity and security | F10: 18000 | G10: Bank Transfer | H10: Paid
A11: 46221 | B11: =IF(A11="","",TEXT(A11,"mmm yyyy")) -> Jul 2026 | C11: Personal Care | D11: Personal | E11: Personal care | F11: 42000 | G11: Card | H11: Paid
A12: 46223 | B12: =IF(A12="","",TEXT(A12,"mmm yyyy")) -> Jul 2026 | C12: Healthcare | D12: Medical | E12: Healthcare | F12: 25000 | G12: Card | H12: Paid
A13: 46225 | B13: =IF(A13="","",TEXT(A13,"mmm yyyy")) -> Jul 2026 | C13: Charity | D13: Support | E13: Charity | F13: 30000 | G13: Bank Transfer | H13: Paid
A14: 46228 | B14: =IF(A14="","",TEXT(A14,"mmm yyyy")) -> Jul 2026 | C14: Education | D14: Learning | E14: Training/materials | F14: 20000 | G14: Bank Transfer | H14: Paid
A15: 46230 | B15: =IF(A15="","",TEXT(A15,"mmm yyyy")) -> Jul 2026 | C15: Travel | D15: Local trip | E15: Travel | F15: 12000 | G15: Cash | H15: Paid
... A29: 46263 | B29: =IF(A29="","",TEXT(A29,"mmm yyyy")) -> Aug 2026 | C29: Miscellaneous | D29: Others | E29: Miscellaneous | F29: 15000 | G29: Cash | H29: Paid
B30: =IF(A30="","",TEXT(A30,"mmm yyyy"))
B31: =IF(A31="","",TEXT(A31,"mmm yyyy"))
B32: =IF(A32="","",TEXT(A32,"mmm yyyy"))
B33: =IF(A33="","",TEXT(A33,"mmm yyyy"))
B34: =IF(A34="","",TEXT(A34,"mmm yyyy"))
B35: =IF(A35="","",TEXT(A35,"mmm yyyy"))
B36: =IF(A36="","",TEXT(A36,"mmm yyyy"))
B37: =IF(A37="","",TEXT(A37,"mmm yyyy"))
B38: =IF(A38="","",TEXT(A38,"mmm yyyy"))
B39: =IF(A39="","",TEXT(A39,"mmm yyyy"))
B40: =IF(A40="","",TEXT(A40,"mmm yyyy"))
B41: =IF(A41="","",TEXT(A41,"mmm yyyy"))
... B500: =IF(A500="","",TEXT(A500,"mmm yyyy"))

Sheet Budget
A1: Monthly Budget Planner
A3: Category | B3: Monthly Budget | C3: Annual Budget | D3: Jul 2026 | E3: Aug 2026 | F3: Sep 2026 | G3: Oct 2026 | H3: Nov 2026 | I3: Dec 2026 | J3: Jan 2027 | K3: Feb 2027 | L3: Mar 2027 | M3: Apr 2027 | N3: May 2027 | O3: Jun 2027 | P3: Year-to-Date Actual | Q3: YTD Variance | R3: YTD % Used | S3: Notes
A4: Rent | B4: 100000 | C4: =B4*12 -> 1200000 | D4: =SUMIFS(Expenses!$F$4:$F$500,Expenses!$B$4:$B$500,D$3,Expenses!$C$4:$C$500,$A4,Expenses!$H$4:$H$500,"Paid") -> 100000 | E4: =SUMIFS(Expenses!$F$4:$F$500,Expenses!$B$4:$B$500,E$3,Expenses!$C$4:$C$500,$A4,Expenses!$H$4:$H$500,"Paid") -> 100000 | F4: =SUMIFS(Expenses!$F$4:$F$500,Expenses!$B$4:$B$500,F$3,Expenses!$C$4:$C$500,$A4,Expenses!$H$4:$H$500,"Paid") -> 0 | G4: =SUMIFS(Expenses!$F$4:$F$500,Expenses!$B$4:$B$500,G$3,Expenses!$C$4:$C$500,$A4,Expenses!$H$4:$H$500,"Paid") -> 0 | H4: =SUMIFS(Expenses!$F$4:$F$500,Expenses!$B$4:$B$500,H$3,Expenses!$C$4:$C$500,$A4,Expenses!$H$4:$H$500,"Paid") -> 0 | I4: =SUMIFS(Expenses!$F$4:$F$500,Expenses!$B$4:$B$500,I$3,Expenses!$C$4:$C$500,$A4,Expenses!$H$4:$H$500,"Paid") -> 0 | J4: =SUMIFS(Expenses!$F$4:$F$500,Expenses!$B$4:$B$500,J$3,Expenses!$C$4:$C$500,$A4,Expenses!$H$4:$H$500,"Paid") -> 0 | K4: =SUMIFS(Expenses!$F$4:$F$500,Expenses!$B$4:$B$500,K$3,Expenses!$C$4:$C$500,$A4,Expenses!$H$4:$H$500,"Paid") -> 0 | ... O4: =SUMIFS(Expenses!$F$4:$F$500,Expenses!$B$4:$B$500,O$3,Expenses!$C$4:$C$500,$A4,Expenses!$H$4:$H$500,"Paid") -> 0 | P4: =SUM(D4:O4) -> 200000 | Q4: =C4-P4 -> 1000000 | R4: =IFERROR(P4/C4,0) -> 0.16666667
A5: Electricity/Security | B5: 20000 | C5: =B5*12 -> 240000 | D5: =SUMIFS(Expenses!$F$4:$F$500,Expenses!$B$4:$B$500,D$3,Expenses!$C$4:$C$500,$A5,Expenses!$H$4:$H$500,"Paid") -> 18000 | E5: =SUMIFS(Expenses!$F$4:$F$500,Expenses!$B$4:$B$500,E$3,Expenses!$C$4:$C$500,$A5,Expenses!$H$4:$H$500,"Paid") -> 22000 | F5: =SUMIFS(Expenses!$F$4:$F$500,Expenses!$B$4:$B$500,F$3,Expenses!$C$4:$C$500,$A5,Expenses!$H$4:$H$500,"Paid") -> 0 | G5: =SUMIFS(Expenses!$F$4:$F$500,Expenses!$B$4:$B$500,G$3,Expenses!$C$4:$C$500,$A5,Expenses!$H$4:$H$500,"Paid") -> 0 | H5: =SUMIFS(Expenses!$F$4:$F$500,Expenses!$B$4:$B$500,H$3,Expenses!$C$4:$C$500,$A5,Expenses!$H$4:$H$500,"Paid") -> 0 | I5: =SUMIFS(Expenses!$F$4:$F$500,Expenses!$B$4:$B$500,I$3,Expenses!$C$4:$C$500,$A5,Expenses!$H$4:$H$500,"Paid") -> 0 | J5: =SUMIFS(Expenses!$F$4:$F$500,Expenses!$B$4:$B$500,J$3,Expenses!$C$4:$C$500,$A5,Expenses!$H$4:$H$500,"Paid") -> 0 | K5: =SUMIFS(Expenses!$F$4:$F$500,Expenses!$B$4:$B$500,K$3,Expenses!$C$4:$C$500,$A5,Expenses!$H$4:$H$500,"Paid") -> 0 | ... O5: =SUMIFS(Expenses!$F$4:$F$500,Expenses!$B$4:$B$500,O$3,Expenses!$C$4:$C$500,$A5,Expenses!$H$4:$H$500,"Paid") -> 0 | P5: =SUM(D5:O5) -> 40000 | Q5: =C5-P5 -> 200000 | R5: =IFERROR(P5/C5,0) -> 0.16666667
A6: Internet/Airtime | B6: 35000 | C6: =B6*12 -> 420000 | D6: =SUMIFS(Expenses!$F$4:$F$500,Expenses!$B$4:$B$500,D$3,Expenses!$C$4:$C$500,$A6,Expenses!$H$4:$H$500,"Paid") -> 35000 | E6: =SUMIFS(Expenses!$F$4:$F$500,Expenses!$B$4:$B$500,E$3,Expenses!$C$4:$C$500,$A6,Expenses!$H$4:$H$500,"Paid") -> 35000 | F6: =SUMIFS(Expenses!$F$4:$F$500,Expenses!$B$4:$B$500,F$3,Expenses!$C$4:$C$500,$A6,Expenses!$H$4:$H$500,"Paid") -> 0 | G6: =SUMIFS(Expenses!$F$4:$F$500,Expenses!$B$4:$B$500,G$3,Expenses!$C$4:$C$500,$A6,Expenses!$H$4:$H$500,"Paid") -> 0 | H6: =SUMIFS(Expenses!$F$4:$F$500,Expenses!$B$4:$B$500,H$3,Expenses!$C$4:$C$500,$A6,Expenses!$H$4:$H$500,"Paid") -> 0 | I6: =SUMIFS(Expenses!$F$4:$F$500,Expenses!$B$4:$B$500,I$3,Expenses!$C$4:$C$500,$A6,Expenses!$H$4:$H$500,"Paid") -> 0 | J6: =SUMIFS(Expenses!$F$4:$F$500,Expenses!$B$4:$B$500,J$3,Expenses!$C$4:$C$500,$A6,Expenses!$H$4:$H$500,"Paid") -> 0 | K6: =SUMIFS(Expenses!$F$4:$F$500,Expenses!$B$4:$B$500,K$3,Expenses!$C$4:$C$500,$A6,Expenses!$H$4:$H$500,"Paid") -> 0 | ... O6: =SUMIFS(Expenses!$F$4:$F$500,Expenses!$B$4:$B$500,O$3,Expenses!$C$4:$C$500,$A6,Expenses!$H$4:$H$500,"Paid") -> 0 | P6: =SUM(D6:O6) -> 70000 | Q6: =C6-P6 -> 350000 | R6: =IFERROR(P6/C6,0) -> 0.16666667
A7: Transport | B7: 50000 | C7: =B7*12 -> 600000 | D7: =SUMIFS(Expenses!$F$4:$F$500,Expenses!$B$4:$B$500,D$3,Expenses!$C$4:$C$500,$A7,Expenses!$H$4:$H$500,"Paid") -> 45000 | E7: =SUMIFS(Expenses!$F$4:$F$500,Expenses!$B$4:$B$500,E$3,Expenses!$C$4:$C$500,$A7,Expenses!$H$4:$H$500,"Paid") -> 50000 | F7: =SUMIFS(Expenses!$F$4:$F$500,Expenses!$B$4:$B$500,F$3,Expenses!$C$4:$C$500,$A7,Expenses!$H$4:$H$500,"Paid") -> 0 | G7: =SUMIFS(Expenses!$F$4:$F$500,Expenses!$B$4:$B$500,G$3,Expenses!$C$4:$C$500,$A7,Expenses!$H$4:$H$500,"Paid") -> 0 | H7: =SUMIFS(Expenses!$F$4:$F$500,Expenses!$B$4:$B$500,H$3,Expenses!$C$4:$C$500,$A7,Expenses!$H$4:$H$500,"Paid") -> 0 | I7: =SUMIFS(Expenses!$F$4:$F$500,Expenses!$B$4:$B$500,I$3,Expenses!$C$4:$C$500,$A7,Expenses!$H$4:$H$500,"Paid") -> 0 | J7: =SUMIFS(Expenses!$F$4:$F$500,Expenses!$B$4:$B$500,J$3,Expenses!$C$4:$C$500,$A7,Expenses!$H$4:$H$500,"Paid") -> 0 | K7: =SUMIFS(Expenses!$F$4:$F$500,Expenses!$B$4:$B$500,K$3,Expenses!$C$4:$C$500,$A7,Expenses!$H$4:$H$500,"Paid") -> 0 | ... O7: =SUMIFS(Expenses!$F$4:$F$500,Expenses!$B$4:$B$500,O$3,Expenses!$C$4:$C$500,$A7,Expenses!$H$4:$H$500,"Paid") -> 0 | P7: =SUM(D7:O7) -> 95000 | Q7: =C7-P7 -> 505000 | R7: =IFERROR(P7/C7,0) -> 0.15833333
A8: Food | B8: 150000 | C8: =B8*12 -> 1800000 | D8: =SUMIFS(Expenses!$F$4:$F$500,Expenses!$B$4:$B$500,D$3,Expenses!$C$4:$C$500,$A8,Expenses!$H$4:$H$500,"Paid") -> 95000 | E8: =SUMIFS(Expenses!$F$4:$F$500,Expenses!$B$4:$B$500,E$3,Expenses!$C$4:$C$500,$A8,Expenses!$H$4:$H$500,"Paid") -> 105000 | F8: =SUMIFS(Expenses!$F$4:$F$500,Expenses!$B$4:$B$500,F$3,Expenses!$C$4:$C$500,$A8,Expenses!$H$4:$H$500,"Paid") -> 0 | G8: =SUMIFS(Expenses!$F$4:$F$500,Expenses!$B$4:$B$500,G$3,Expenses!$C$4:$C$500,$A8,Expenses!$H$4:$H$500,"Paid") -> 0 | H8: =SUMIFS(Expenses!$F$4:$F$500,Expenses!$B$4:$B$500,H$3,Expenses!$C$4:$C$500,$A8,Expenses!$H$4:$H$500,"Paid") -> 0 | I8: =SUMIFS(Expenses!$F$4:$F$500,Expenses!$B$4:$B$500,I$3,Expenses!$C$4:$C$500,$A8,Expenses!$H$4:$H$500,"Paid") -> 0 | J8: =SUMIFS(Expenses!$F$4:$F$500,Expenses!$B$4:$B$500,J$3,Expenses!$C$4:$C$500,$A8,Expenses!$H$4:$H$500,"Paid") -> 0 | K8: =SUMIFS(Expenses!$F$4:$F$500,Expenses!$B$4:$B$500,K$3,Expenses!$C$4:$C$500,$A8,Expenses!$H$4:$H$500,"Paid") -> 0 | ... O8: =SUMIFS(Expenses!$F$4:$F$500,Expenses!$B$4:$B$500,O$3,Expenses!$C$4:$C$500,$A8,Expenses!$H$4:$H$500,"Paid") -> 0 | P8: =SUM(D8:O8) -> 200000 | Q8: =C8-P8 -> 1600000 | R8: =IFERROR(P8/C8,0) -> 0.11111111
A9: Personal Care | B9: 50000 | C9: =B9*12 -> 600000 | D9: =SUMIFS(Expenses!$F$4:$F$500,Expenses!$B$4:$B$500,D$3,Expenses!$C$4:$C$500,$A9,Expenses!$H$4:$H$500,"Paid") -> 42000 | E9: =SUMIFS(Expenses!$F$4:$F$500,Expenses!$B$4:$B$500,E$3,Expenses!$C$4:$C$500,$A9,Expenses!$H$4:$H$500,"Paid") -> 45000 | F9: =SUMIFS(Expenses!$F$4:$F$500,Expenses!$B$4:$B$500,F$3,Expenses!$C$4:$C$500,$A9,Expenses!$H$4:$H$500,"Paid") -> 0 | G9: =SUMIFS(Expenses!$F$4:$F$500,Expenses!$B$4:$B$500,G$3,Expenses!$C$4:$C$500,$A9,Expenses!$H$4:$H$500,"Paid") -> 0 | H9: =SUMIFS(Expenses!$F$4:$F$500,Expenses!$B$4:$B$500,H$3,Expenses!$C$4:$C$500,$A9,Expenses!$H$4:$H$500,"Paid") -> 0 | I9: =SUMIFS(Expenses!$F$4:$F$500,Expenses!$B$4:$B$500,I$3,Expenses!$C$4:$C$500,$A9,Expenses!$H$4:$H$500,"Paid") -> 0 | J9: =SUMIFS(Expenses!$F$4:$F$500,Expenses!$B$4:$B$500,J$3,Expenses!$C$4:$C$500,$A9,Expenses!$H$4:$H$500,"Paid") -> 0 | K9: =SUMIFS(Expenses!$F$4:$F$500,Expenses!$B$4:$B$500,K$3,Expenses!$C$4:$C$500,$A9,Expenses!$H$4:$H$500,"Paid") -> 0 | ... O9: =SUMIFS(Expenses!$F$4:$F$500,Expenses!$B$4:$B$500,O$3,Expenses!$C$4:$C$500,$A9,Expenses!$H$4:$H$500,"Paid") -> 0 | P9: =SUM(D9:O9) -> 87000 | Q9: =C9-P9 -> 513000 | R9: =IFERROR(P9/C9,0) -> 0.145
A10: Healthcare | B10: 50000 | C10: =B10*12 -> 600000 | D10: =SUMIFS(Expenses!$F$4:$F$500,Expenses!$B$4:$B$500,D$3,Expenses!$C$4:$C$500,$A10,Expenses!$H$4:$H$500,"Paid") -> 25000 | E10: =SUMIFS(Expenses!$F$4:$F$500,Expenses!$B$4:$B$500,E$3,Expenses!$C$4:$C$500,$A10,Expenses!$H$4:$H$500,"Paid") -> 30000 | F10: =SUMIFS(Expenses!$F$4:$F$500,Expenses!$B$4:$B$500,F$3,Expenses!$C$4:$C$500,$A10,Expenses!$H$4:$H$500,"Paid") -> 0 | G10: =SUMIFS(Expenses!$F$4:$F$500,Expenses!$B$4:$B$500,G$3,Expenses!$C$4:$C$500,$A10,Expenses!$H$4:$H$500,"Paid") -> 0 | H10: =SUMIFS(Expenses!$F$4:$F$500,Expenses!$B$4:$B$500,H$3,Expenses!$C$4:$C$500,$A10,Expenses!$H$4:$H$500,"Paid") -> 0 | I10: =SUMIFS(Expenses!$F$4:$F$500,Expenses!$B$4:$B$500,I$3,Expenses!$C$4:$C$500,$A10,Expenses!$H$4:$H$500,"Paid") -> 0 | J10: =SUMIFS(Expenses!$F$4:$F$500,Expenses!$B$4:$B$500,J$3,Expenses!$C$4:$C$500,$A10,Expenses!$H$4:$H$500,"Paid") -> 0 | K10: =SUMIFS(Expenses!$F$4:$F$500,Expenses!$B$4:$B$500,K$3,Expenses!$C$4:$C$500,$A10,Expenses!$H$4:$H$500,"Paid") -> 0 | ... O10: =SUMIFS(Expenses!$F$4:$F$500,Expenses!$B$4:$B$500,O$3,Expenses!$C$4:$C$500,$A10,Expenses!$H$4:$H$500,"Paid") -> 0 | P10: =SUM(D10:O10) -> 55000 | Q10: =C10-P10 -> 545000 | R10: =IFERROR(P10/C10,0) -> 0.091666667
A11: Family Support | B11: 80000 | C11: =B11*12 -> 960000 | D11: =SUMIFS(Expenses!$F$4:$F$500,Expenses!$B$4:$B$500,D$3,Expenses!$C$4:$C$500,$A11,Expenses!$H$4:$H$500,"Paid") -> 80000 | E11: =SUMIFS(Expenses!$F$4:$F$500,Expenses!$B$4:$B$500,E$3,Expenses!$C$4:$C$500,$A11,Expenses!$H$4:$H$500,"Paid") -> 80000 | F11: =SUMIFS(Expenses!$F$4:$F$500,Expenses!$B$4:$B$500,F$3,Expenses!$C$4:$C$500,$A11,Expenses!$H$4:$H$500,"Paid") -> 0 | G11: =SUMIFS(Expenses!$F$4:$F$500,Expenses!$B$4:$B$500,G$3,Expenses!$C$4:$C$500,$A11,Expenses!$H$4:$H$500,"Paid") -> 0 | H11: =SUMIFS(Expenses!$F$4:$F$500,Expenses!$B$4:$B$500,H$3,Expenses!$C$4:$C$500,$A11,Expenses!$H$4:$H$500,"Paid") -> 0 | I11: =SUMIFS(Expenses!$F$4:$F$500,Expenses!$B$4:$B$500,I$3,Expenses!$C$4:$C$500,$A11,Expenses!$H$4:$H$500,"Paid") -> 0 | J11: =SUMIFS(Expenses!$F$4:$F$500,Expenses!$B$4:$B$500,J$3,Expenses!$C$4:$C$500,$A11,Expenses!$H$4:$H$500,"Paid") -> 0 | K11: =SUMIFS(Expenses!$F$4:$F$500,Expenses!$B$4:$B$500,K$3,Expenses!$C$4:$C$500,$A11,Expenses!$H$4:$H$500,"Paid") -> 0 | ... O11: =SUMIFS(Expenses!$F$4:$F$500,Expenses!$B$4:$B$500,O$3,Expenses!$C$4:$C$500,$A11,Expenses!$H$4:$H$500,"Paid") -> 0 | P11: =SUM(D11:O11) -> 160000 | Q11: =C11-P11 -> 800000 | R11: =IFERROR(P11/C11,0) -> 0.16666667
A12: Church Giving | B12: 120000 | C12: =B12*12 -> 1440000 | D12: =SUMIFS(Expenses!$F$4:$F$500,Expenses!$B$4:$B$500,D$3,Expenses!$C$4:$C$500,$A12,Expenses!$H$4:$H$500,"Paid") -> 120000 | E12: =SUMIFS(Expenses!$F$4:$F$500,Expenses!$B$4:$B$500,E$3,Expenses!$C$4:$C$500,$A12,Expenses!$H$4:$H$500,"Paid") -> 120000 | F12: =SUMIFS(Expenses!$F$4:$F$500,Expenses!$B$4:$B$500,F$3,Expenses!$C$4:$C$500,$A12,Expenses!$H$4:$H$500,"Paid") -> 0 | G12: =SUMIFS(Expenses!$F$4:$F$500,Expenses!$B$4:$B$500,G$3,Expenses!$C$4:$C$500,$A12,Expenses!$H$4:$H$500,"Paid") -> 0 | H12: =SUMIFS(Expenses!$F$4:$F$500,Expenses!$B$4:$B$500,H$3,Expenses!$C$4:$C$500,$A12,Expenses!$H$4:$H$500,"Paid") -> 0 | I12: =SUMIFS(Expenses!$F$4:$F$500,Expenses!$B$4:$B$500,I$3,Expenses!$C$4:$C$500,$A12,Expenses!$H$4:$H$500,"Paid") -> 0 | J12: =SUMIFS(Expenses!$F$4:$F$500,Expenses!$B$4:$B$500,J$3,Expenses!$C$4:$C$500,$A12,Expenses!$H$4:$H$500,"Paid") -> 0 | K12: =SUMIFS(Expenses!$F$4:$F$500,Expenses!$B$4:$B$500,K$3,Expenses!$C$4:$C$500,$A12,Expenses!$H$4:$H$500,"Paid") -> 0 | ... O12: =SUMIFS(Expenses!$F$4:$F$500,Expenses!$B$4:$B$500,O$3,Expenses!$C$4:$C$500,$A12,Expenses!$H$4:$H$500,"Paid") -> 0 | P12: =SUM(D12:O12) -> 240000 | Q12: =C12-P12 -> 1200000 | R12: =IFERROR(P12/C12,0) -> 0.16666667
A13: Charity | B13: 30000 | C13: =B13*12 -> 360000 | D13: =SUMIFS(Expenses!$F$4:$F$500,Expenses!$B$4:$B$500,D$3,Expenses!$C$4:$C$500,$A13,Expenses!$H$4:$H$500,"Paid") -> 30000 | E13: =SUMIFS(Expenses!$F$4:$F$500,Expenses!$B$4:$B$500,E$3,Expenses!$C$4:$C$500,$A13,Expenses!$H$4:$H$500,"Paid") -> 30000 | F13: =SUMIFS(Expenses!$F$4:$F$500,Expenses!$B$4:$B$500,F$3,Expenses!$C$4:$C$500,$A13,Expenses!$H$4:$H$500,"Paid") -> 0 | G13: =SUMIFS(Expenses!$F$4:$F$500,Expenses!$B$4:$B$500,G$3,Expenses!$C$4:$C$500,$A13,Expenses!$H$4:$H$500,"Paid") -> 0 | H13: =SUMIFS(Expenses!$F$4:$F$500,Expenses!$B$4:$B$500,H$3,Expenses!$C$4:$C$500,$A13,Expenses!$H$4:$H$500,"Paid") -> 0 | I13: =SUMIFS(Expenses!$F$4:$F$500,Expenses!$B$4:$B$500,I$3,Expenses!$C$4:$C$500,$A13,Expenses!$H$4:$H$500,"Paid") -> 0 | J13: =SUMIFS(Expenses!$F$4:$F$500,Expenses!$B$4:$B$500,J$3,Expenses!$C$4:$C$500,$A13,Expenses!$H$4:$H$500,"Paid") -> 0 | K13: =SUMIFS(Expenses!$F$4:$F$500,Expenses!$B$4:$B$500,K$3,Expenses!$C$4:$C$500,$A13,Expenses!$H$4:$H$500,"Paid") -> 0 | ... O13: =SUMIFS(Expenses!$F$4:$F$500,Expenses!$B$4:$B$500,O$3,Expenses!$C$4:$C$500,$A13,Expenses!$H$4:$H$500,"Paid") -> 0 | P13: =SUM(D13:O13) -> 60000 | Q13: =C13-P13 -> 300000 | R13: =IFERROR(P13/C13,0) -> 0.16666667
A14: Education | B14: 20000 | C14: =B14*12 -> 240000 | D14: =SUMIFS(Expenses!$F$4:$F$500,Expenses!$B$4:$B$500,D$3,Expenses!$C$4:$C$500,$A14,Expenses!$H$4:$H$500,"Paid") -> 20000 | E14: =SUMIFS(Expenses!$F$4:$F$500,Expenses!$B$4:$B$500,E$3,Expenses!$C$4:$C$500,$A14,Expenses!$H$4:$H$500,"Paid") -> 25000 | F14: =SUMIFS(Expenses!$F$4:$F$500,Expenses!$B$4:$B$500,F$3,Expenses!$C$4:$C$500,$A14,Expenses!$H$4:$H$500,"Paid") -> 0 | G14: =SUMIFS(Expenses!$F$4:$F$500,Expenses!$B$4:$B$500,G$3,Expenses!$C$4:$C$500,$A14,Expenses!$H$4:$H$500,"Paid") -> 0 | H14: =SUMIFS(Expenses!$F$4:$F$500,Expenses!$B$4:$B$500,H$3,Expenses!$C$4:$C$500,$A14,Expenses!$H$4:$H$500,"Paid") -> 0 | I14: =SUMIFS(Expenses!$F$4:$F$500,Expenses!$B$4:$B$500,I$3,Expenses!$C$4:$C$500,$A14,Expenses!$H$4:$H$500,"Paid") -> 0 | J14: =SUMIFS(Expenses!$F$4:$F$500,Expenses!$B$4:$B$500,J$3,Expenses!$C$4:$C$500,$A14,Expenses!$H$4:$H$500,"Paid") -> 0 | K14: =SUMIFS(Expenses!$F$4:$F$500,Expenses!$B$4:$B$500,K$3,Expenses!$C$4:$C$500,$A14,Expenses!$H$4:$H$500,"Paid") -> 0 | ... O14: =SUMIFS(Expenses!$F$4:$F$500,Expenses!$B$4:$B$500,O$3,Expenses!$C$4:$C$500,$A14,Expenses!$H$4:$H$500,"Paid") -> 0 | P14: =SUM(D14:O14) -> 45000 | Q14: =C14-P14 -> 195000 | R14: =IFERROR(P14/C14,0) -> 0.1875
A15: Travel | B15: 20000 | C15: =B15*12 -> 240000 | D15: =SUMIFS(Expenses!$F$4:$F$500,Expenses!$B$4:$B$500,D$3,Expenses!$C$4:$C$500,$A15,Expenses!$H$4:$H$500,"Paid") -> 12000 | E15: =SUMIFS(Expenses!$F$4:$F$500,Expenses!$B$4:$B$500,E$3,Expenses!$C$4:$C$500,$A15,Expenses!$H$4:$H$500,"Paid") -> 17000 | F15: =SUMIFS(Expenses!$F$4:$F$500,Expenses!$B$4:$B$500,F$3,Expenses!$C$4:$C$500,$A15,Expenses!$H$4:$H$500,"Paid") -> 0 | G15: =SUMIFS(Expenses!$F$4:$F$500,Expenses!$B$4:$B$500,G$3,Expenses!$C$4:$C$500,$A15,Expenses!$H$4:$H$500,"Paid") -> 0 | H15: =SUMIFS(Expenses!$F$4:$F$500,Expenses!$B$4:$B$500,H$3,Expenses!$C$4:$C$500,$A15,Expenses!$H$4:$H$500,"Paid") -> 0 | I15: =SUMIFS(Expenses!$F$4:$F$500,Expenses!$B$4:$B$500,I$3,Expenses!$C$4:$C$500,$A15,Expenses!$H$4:$H$500,"Paid") -> 0 | J15: =SUMIFS(Expenses!$F$4:$F$500,Expenses!$B$4:$B$500,J$3,Expenses!$C$4:$C$500,$A15,Expenses!$H$4:$H$500,"Paid") -> 0 | K15: =SUMIFS(Expenses!$F$4:$F$500,Expenses!$B$4:$B$500,K$3,Expenses!$C$4:$C$500,$A15,Expenses!$H$4:$H$500,"Paid") -> 0 | ... O15: =SUMIFS(Expenses!$F$4:$F$500,Expenses!$B$4:$B$500,O$3,Expenses!$C$4:$C$500,$A15,Expenses!$H$4:$H$500,"Paid") -> 0 | P15: =SUM(D15:O15) -> 29000 | Q15: =C15-P15 -> 211000 | R15: =IFERROR(P15/C15,0) -> 0.12083333
A16: Miscellaneous | B16: 15000 | C16: =B16*12 -> 180000 | D16: =SUMIFS(Expenses!$F$4:$F$500,Expenses!$B$4:$B$500,D$3,Expenses!$C$4:$C$500,$A16,Expenses!$H$4:$H$500,"Paid") -> 18000 | E16: =SUMIFS(Expenses!$F$4:$F$500,Expenses!$B$4:$B$500,E$3,Expenses!$C$4:$C$500,$A16,Expenses!$H$4:$H$500,"Paid") -> 15000 | F16: =SUMIFS(Expenses!$F$4:$F$500,Expenses!$B$4:$B$500,F$3,Expenses!$C$4:$C$500,$A16,Expenses!$H$4:$H$500,"Paid") -> 0 | G16: =SUMIFS(Expenses!$F$4:$F$500,Expenses!$B$4:$B$500,G$3,Expenses!$C$4:$C$500,$A16,Expenses!$H$4:$H$500,"Paid") -> 0 | H16: =SUMIFS(Expenses!$F$4:$F$500,Expenses!$B$4:$B$500,H$3,Expenses!$C$4:$C$500,$A16,Expenses!$H$4:$H$500,"Paid") -> 0 | I16: =SUMIFS(Expenses!$F$4:$F$500,Expenses!$B$4:$B$500,I$3,Expenses!$C$4:$C$500,$A16,Expenses!$H$4:$H$500,"Paid") -> 0 | J16: =SUMIFS(Expenses!$F$4:$F$500,Expenses!$B$4:$B$500,J$3,Expenses!$C$4:$C$500,$A16,Expenses!$H$4:$H$500,"Paid") -> 0 | K16: =SUMIFS(Expenses!$F$4:$F$500,Expenses!$B$4:$B$500,K$3,Expenses!$C$4:$C$500,$A16,Expenses!$H$4:$H$500,"Paid") -> 0 | ... O16: =SUMIFS(Expenses!$F$4:$F$500,Expenses!$B$4:$B$500,O$3,Expenses!$C$4:$C$500,$A16,Expenses!$H$4:$H$500,"Paid") -> 0 | P16: =SUM(D16:O16) -> 33000 | Q16: =C16-P16 -> 147000 | R16: =IFERROR(P16/C16,0) -> 0.18333333
A17: TOTAL | B17: =SUM(B4:B16) -> 740000 | C17: =SUM(C4:C16) -> 8880000 | D17: =SUM(D4:D16) -> 640000 | E17: =SUM(E4:E16) -> 674000 | F17: =SUM(F4:F16) -> 0 | G17: =SUM(G4:G16) -> 0 | H17: =SUM(H4:H16) -> 0 | I17: =SUM(I4:I16) -> 0 | ... Q17: =SUM(Q4:Q16) -> 7566000 | R17: =IFERROR(P17/C17,0) -> 0.14797297

Sheet Savings
A1: Savings Tracker
A3: Date | B3: Month | C3: Savings Type | D3: Amount | E3: Target/Account | F3: Status | G3: Notes
A4: 46214 | B4: =IF(A4="","",TEXT(A4,"mmm yyyy")) -> Jul 2026 | C4: Emergency Fund | D4: 300000 | E4: Emergency Fund | F4: Completed
A5: 46245 | B5: =IF(A5="","",TEXT(A5,"mmm yyyy")) -> Aug 2026 | C5: Emergency Fund | D5: 300000 | E5: Emergency Fund | F5: Completed
A6: 46276 | B6: =IF(A6="","",TEXT(A6,"mmm yyyy")) -> Sep 2026 | C6: Emergency Fund | D6: 300000 | E6: Emergency Fund | F6: Planned
B7: =IF(A7="","",TEXT(A7,"mmm yyyy"))
B8: =IF(A8="","",TEXT(A8,"mmm yyyy"))
B9: =IF(A9="","",TEXT(A9,"mmm yyyy"))
B10: =IF(A10="","",TEXT(A10,"mmm yyyy"))
B11: =IF(A11="","",TEXT(A11,"mmm yyyy"))
B12: =IF(A12="","",TEXT(A12,"mmm yyyy"))
B13: =IF(A13="","",TEXT(A13,"mmm yyyy"))
B14: =IF(A14="","",TEXT(A14,"mmm yyyy"))
B15: =IF(A15="","",TEXT(A15,"mmm yyyy"))
B16: =IF(A16="","",TEXT(A16,"mmm yyyy"))
B17: =IF(A17="","",TEXT(A17,"mmm yyyy"))
B18: =IF(A18="","",TEXT(A18,"mmm yyyy"))
... B200: =IF(A200="","",TEXT(A200,"mmm yyyy"))

Sheet Loans
A1: Loan Tracker
A3: Loan Name | B3: Lender | C3: Original Amount | D3: Interest Rate | E3: Start Date | F3: Due Date | G3: Payment Month | H3: Payment Amount | I3: Status | J3: Outstanding Balance | K3: Notes
A4: Example Loan | B4: Lender Name | C4: 500000 | D4: 0.1 | E4: 46204 | F4: 46387 | G4: Jul 2026 | H4: 50000 | I4: Paid | J4: =IF(A4="","",MAX(0,C4*(1+D4)-SUMIFS($H$4:$H$200,$A$4:$A$200,A4,$I$4:$I$200,"Paid"))) -> 450000 | K4: Replace with your real loan
A5: Example Loan | B5: Lender Name | C5: 500000 | D5: 0.1 | E5: 46204 | F5: 46387 | G5: Aug 2026 | H5: 50000 | I5: Paid | J5: =IF(A5="","",MAX(0,C5*(1+D5)-SUMIFS($H$4:$H$200,$A$4:$A$200,A5,$I$4:$I$200,"Paid"))) -> 450000 | K5: Replace with your real loan
A6: Example Loan | B6: Lender Name | C6: 500000 | D6: 0.1 | E6: 46204 | F6: 46387 | G6: Sep 2026 | H6: 50000 | I6: Planned | J6: =IF(A6="","",MAX(0,C6*(1+D6)-SUMIFS($H$4:$H$200,$A$4:$A$200,A6,$I$4:$I$200,"Paid"))) -> 450000 | K6: Replace with your real loan
J7: =IF(A7="","",MAX(0,C7*(1+D7)-SUMIFS($H$4:$H$200,$A$4:$A$200,A7,$I$4:$I$200,"Paid")))
J8: =IF(A8="","",MAX(0,C8*(1+D8)-SUMIFS($H$4:$H$200,$A$4:$A$200,A8,$I$4:$I$200,"Paid")))
J9: =IF(A9="","",MAX(0,C9*(1+D9)-SUMIFS($H$4:$H$200,$A$4:$A$200,A9,$I$4:$I$200,"Paid")))
J10: =IF(A10="","",MAX(0,C10*(1+D10)-SUMIFS($H$4:$H$200,$A$4:$A$200,A10,$I$4:$I$200,"Paid")))
J11: =IF(A11="","",MAX(0,C11*(1+D11)-SUMIFS($H$4:$H$200,$A$4:$A$200,A11,$I$4:$I$200,"Paid")))
J12: =IF(A12="","",MAX(0,C12*(1+D12)-SUMIFS($H$4:$H$200,$A$4:$A$200,A12,$I$4:$I$200,"Paid")))
J13: =IF(A13="","",MAX(0,C13*(1+D13)-SUMIFS($H$4:$H$200,$A$4:$A$200,A13,$I$4:$I$200,"Paid")))
J14: =IF(A14="","",MAX(0,C14*(1+D14)-SUMIFS($H$4:$H$200,$A$4:$A$200,A14,$I$4:$I$200,"Paid")))
J15: =IF(A15="","",MAX(0,C15*(1+D15)-SUMIFS($H$4:$H$200,$A$4:$A$200,A15,$I$4:$I$200,"Paid")))
J16: =IF(A16="","",MAX(0,C16*(1+D16)-SUMIFS($H$4:$H$200,$A$4:$A$200,A16,$I$4:$I$200,"Paid")))
J17: =IF(A17="","",MAX(0,C17*(1+D17)-SUMIFS($H$4:$H$200,$A$4:$A$200,A17,$I$4:$I$200,"Paid")))
J18: =IF(A18="","",MAX(0,C18*(1+D18)-SUMIFS($H$4:$H$200,$A$4:$A$200,A18,$I$4:$I$200,"Paid")))
... J200: =IF(A200="","",MAX(0,C200*(1+D200)-SUMIFS($H$4:$H$200,$A$4:$A$200,A200,$I$4:$I$200,"Paid")))

Sheet Goals
A1: Financial Goals Tracker
A3: Goal | B3: Target Amount | C3: Current Saved | D3: Remaining | E3: Target Date | F3: Monthly Required | G3: Status | H3: Notes
A4: Emergency Fund | B4: 4440000 | C4: =SUMIFS(Savings!$D$4:$D$200,Savings!$E$4:$E$200,A4,Savings!$F$4:$F$200,"Completed") -> 600000 | D4: =IF(A4="","",MAX(0,B4-C4)) -> 3840000 | E4: 46568 | F4: =IF(A4="","",IFERROR(D4/MAX(1,DATEDIF(TODAY(),E4,"m")),D4)) -> 384000 | G4: In Progress | H4: Target based on 6 months of ₦740,000 monthly budget
A5: Laptop Upgrade | B5: 700000 | C5: =0 -> 0 | D5: =IF(A5="","",MAX(0,B5-C5)) -> 700000 | E5: 46387 | F5: =IF(A5="","",IFERROR(D5/MAX(1,DATEDIF(TODAY(),E5,"m")),D5)) -> 175000 | G5: Not Started | H5: Cybersecurity laptop target
A6: Training/Certification | B6: 300000 | C6: =0 -> 0 | D6: =IF(A6="","",MAX(0,B6-C6)) -> 300000 | E6: 46477 | F6: =IF(A6="","",IFERROR(D6/MAX(1,DATEDIF(TODAY(),E6,"m")),D6)) -> 42857.143 | G6: Not Started | H6: Professional development
D7: =IF(A7="","",MAX(0,B7-C7)) | F7: =IF(A7="","",IFERROR(D7/MAX(1,DATEDIF(TODAY(),E7,"m")),D7))
D8: =IF(A8="","",MAX(0,B8-C8)) | F8: =IF(A8="","",IFERROR(D8/MAX(1,DATEDIF(TODAY(),E8,"m")),D8))
D9: =IF(A9="","",MAX(0,B9-C9)) | F9: =IF(A9="","",IFERROR(D9/MAX(1,DATEDIF(TODAY(),E9,"m")),D9))
D10: =IF(A10="","",MAX(0,B10-C10)) | F10: =IF(A10="","",IFERROR(D10/MAX(1,DATEDIF(TODAY(),E10,"m")),D10))
D11: =IF(A11="","",MAX(0,B11-C11)) | F11: =IF(A11="","",IFERROR(D11/MAX(1,DATEDIF(TODAY(),E11,"m")),D11))
D12: =IF(A12="","",MAX(0,B12-C12)) | F12: =IF(A12="","",IFERROR(D12/MAX(1,DATEDIF(TODAY(),E12,"m")),D12))
D13: =IF(A13="","",MAX(0,B13-C13)) | F13: =IF(A13="","",IFERROR(D13/MAX(1,DATEDIF(TODAY(),E13,"m")),D13))
D14: =IF(A14="","",MAX(0,B14-C14)) | F14: =IF(A14="","",IFERROR(D14/MAX(1,DATEDIF(TODAY(),E14,"m")),D14))
D15: =IF(A15="","",MAX(0,B15-C15)) | F15: =IF(A15="","",IFERROR(D15/MAX(1,DATEDIF(TODAY(),E15,"m")),D15))
D16: =IF(A16="","",MAX(0,B16-C16)) | F16: =IF(A16="","",IFERROR(D16/MAX(1,DATEDIF(TODAY(),E16,"m")),D16))
D17: =IF(A17="","",MAX(0,B17-C17)) | F17: =IF(A17="","",IFERROR(D17/MAX(1,DATEDIF(TODAY(),E17,"m")),D17))
D18: =IF(A18="","",MAX(0,B18-C18)) | F18: =IF(A18="","",IFERROR(D18/MAX(1,DATEDIF(TODAY(),E18,"m")),D18))
... D200: =IF(A200="","",MAX(0,B200-C200)) | F200: =IF(A200="","",IFERROR(D200/MAX(1,DATEDIF(TODAY(),E200,"m")),D200))

Sheet Monthly Summary
A1: Monthly Summary
A3: Month | B3: Income | C3: Expenses | D3: Net Cash Flow | E3: Savings | F3: Loan Payments | G3: Budgeted Expenses | H3: Budget Variance | I3: Savings Rate | J3: Notes
A4: Jul 2026 | B4: =SUMIFS(Income!$F$4:$F$200,Income!$B$4:$B$200,$A4,Income!$G$4:$G$200,"Received") -> 1650000 | C4: =SUMIFS(Expenses!$F$4:$F$500,Expenses!$B$4:$B$500,$A4,Expenses!$H$4:$H$500,"Paid") -> 640000 | D4: =B4-C4 -> 1010000 | E4: =SUMIFS(Savings!$D$4:$D$200,Savings!$B$4:$B$200,$A4,Savings!$F$4:$F$200,"Completed") -> 300000 | F4: =SUMIFS(Loans!$H$4:$H$200,Loans!$G$4:$G$200,$A4,Loans!$I$4:$I$200,"Paid") -> 50000 | G4: =Budget!$B$17 -> 740000 | H4: =G4-C4 -> 100000 | I4: =IFERROR(E4/B4,0) -> 0.18181818
A5: Aug 2026 | B5: =SUMIFS(Income!$F$4:$F$200,Income!$B$4:$B$200,$A5,Income!$G$4:$G$200,"Received") -> 1700000 | C5: =SUMIFS(Expenses!$F$4:$F$500,Expenses!$B$4:$B$500,$A5,Expenses!$H$4:$H$500,"Paid") -> 674000 | D5: =B5-C5 -> 1026000 | E5: =SUMIFS(Savings!$D$4:$D$200,Savings!$B$4:$B$200,$A5,Savings!$F$4:$F$200,"Completed") -> 300000 | F5: =SUMIFS(Loans!$H$4:$H$200,Loans!$G$4:$G$200,$A5,Loans!$I$4:$I$200,"Paid") -> 50000 | G5: =Budget!$B$17 -> 740000 | H5: =G5-C5 -> 66000 | I5: =IFERROR(E5/B5,0) -> 0.17647059
A6: Sep 2026 | B6: =SUMIFS(Income!$F$4:$F$200,Income!$B$4:$B$200,$A6,Income!$G$4:$G$200,"Received") -> 0 | C6: =SUMIFS(Expenses!$F$4:$F$500,Expenses!$B$4:$B$500,$A6,Expenses!$H$4:$H$500,"Paid") -> 0 | D6: =B6-C6 -> 0 | E6: =SUMIFS(Savings!$D$4:$D$200,Savings!$B$4:$B$200,$A6,Savings!$F$4:$F$200,"Completed") -> 0 | F6: =SUMIFS(Loans!$H$4:$H$200,Loans!$G$4:$G$200,$A6,Loans!$I$4:$I$200,"Paid") -> 0 | G6: =Budget!$B$17 -> 740000 | H6: =G6-C6 -> 740000 | I6: =IFERROR(E6/B6,0) -> 0
A7: Oct 2026 | B7: =SUMIFS(Income!$F$4:$F$200,Income!$B$4:$B$200,$A7,Income!$G$4:$G$200,"Received") -> 0 | C7: =SUMIFS(Expenses!$F$4:$F$500,Expenses!$B$4:$B$500,$A7,Expenses!$H$4:$H$500,"Paid") -> 0 | D7: =B7-C7 -> 0 | E7: =SUMIFS(Savings!$D$4:$D$200,Savings!$B$4:$B$200,$A7,Savings!$F$4:$F$200,"Completed") -> 0 | F7: =SUMIFS(Loans!$H$4:$H$200,Loans!$G$4:$G$200,$A7,Loans!$I$4:$I$200,"Paid") -> 0 | G7: =Budget!$B$17 -> 740000 | H7: =G7-C7 -> 740000 | I7: =IFERROR(E7/B7,0) -> 0
A8: Nov 2026 | B8: =SUMIFS(Income!$F$4:$F$200,Income!$B$4:$B$200,$A8,Income!$G$4:$G$200,"Received") -> 0 | C8: =SUMIFS(Expenses!$F$4:$F$500,Expenses!$B$4:$B$500,$A8,Expenses!$H$4:$H$500,"Paid") -> 0 | D8: =B8-C8 -> 0 | E8: =SUMIFS(Savings!$D$4:$D$200,Savings!$B$4:$B$200,$A8,Savings!$F$4:$F$200,"Completed") -> 0 | F8: =SUMIFS(Loans!$H$4:$H$200,Loans!$G$4:$G$200,$A8,Loans!$I$4:$I$200,"Paid") -> 0 | G8: =Budget!$B$17 -> 740000 | H8: =G8-C8 -> 740000 | I8: =IFERROR(E8/B8,0) -> 0
A9: Dec 2026 | B9: =SUMIFS(Income!$F$4:$F$200,Income!$B$4:$B$200,$A9,Income!$G$4:$G$200,"Received") -> 0 | C9: =SUMIFS(Expenses!$F$4:$F$500,Expenses!$B$4:$B$500,$A9,Expenses!$H$4:$H$500,"Paid") -> 0 | D9: =B9-C9 -> 0 | E9: =SUMIFS(Savings!$D$4:$D$200,Savings!$B$4:$B$200,$A9,Savings!$F$4:$F$200,"Completed") -> 0 | F9: =SUMIFS(Loans!$H$4:$H$200,Loans!$G$4:$G$200,$A9,Loans!$I$4:$I$200,"Paid") -> 0 | G9: =Budget!$B$17 -> 740000 | H9: =G9-C9 -> 740000 | I9: =IFERROR(E9/B9,0) -> 0
A10: Jan 2027 | B10: =SUMIFS(Income!$F$4:$F$200,Income!$B$4:$B$200,$A10,Income!$G$4:$G$200,"Received") -> 0 | C10: =SUMIFS(Expenses!$F$4:$F$500,Expenses!$B$4:$B$500,$A10,Expenses!$H$4:$H$500,"Paid") -> 0 | D10: =B10-C10 -> 0 | E10: =SUMIFS(Savings!$D$4:$D$200,Savings!$B$4:$B$200,$A10,Savings!$F$4:$F$200,"Completed") -> 0 | F10: =SUMIFS(Loans!$H$4:$H$200,Loans!$G$4:$G$200,$A10,Loans!$I$4:$I$200,"Paid") -> 0 | G10: =Budget!$B$17 -> 740000 | H10: =G10-C10 -> 740000 | I10: =IFERROR(E10/B10,0) -> 0
A11: Feb 2027 | B11: =SUMIFS(Income!$F$4:$F$200,Income!$B$4:$B$200,$A11,Income!$G$4:$G$200,"Received") -> 0 | C11: =SUMIFS(Expenses!$F$4:$F$500,Expenses!$B$4:$B$500,$A11,Expenses!$H$4:$H$500,"Paid") -> 0 | D11: =B11-C11 -> 0 | E11: =SUMIFS(Savings!$D$4:$D$200,Savings!$B$4:$B$200,$A11,Savings!$F$4:$F$200,"Completed") -> 0 | F11: =SUMIFS(Loans!$H$4:$H$200,Loans!$G$4:$G$200,$A11,Loans!$I$4:$I$200,"Paid") -> 0 | G11: =Budget!$B$17 -> 740000 | H11: =G11-C11 -> 740000 | I11: =IFERROR(E11/B11,0) -> 0
A12: Mar 2027 | B12: =SUMIFS(Income!$F$4:$F$200,Income!$B$4:$B$200,$A12,Income!$G$4:$G$200,"Received") -> 0 | C12: =SUMIFS(Expenses!$F$4:$F$500,Expenses!$B$4:$B$500,$A12,Expenses!$H$4:$H$500,"Paid") -> 0 | D12: =B12-C12 -> 0 | E12: =SUMIFS(Savings!$D$4:$D$200,Savings!$B$4:$B$200,$A12,Savings!$F$4:$F$200,"Completed") -> 0 | F12: =SUMIFS(Loans!$H$4:$H$200,Loans!$G$4:$G$200,$A12,Loans!$I$4:$I$200,"Paid") -> 0 | G12: =Budget!$B$17 -> 740000 | H12: =G12-C12 -> 740000 | I12: =IFERROR(E12/B12,0) -> 0
A13: Apr 2027 | B13: =SUMIFS(Income!$F$4:$F$200,Income!$B$4:$B$200,$A13,Income!$G$4:$G$200,"Received") -> 0 | C13: =SUMIFS(Expenses!$F$4:$F$500,Expenses!$B$4:$B$500,$A13,Expenses!$H$4:$H$500,"Paid") -> 0 | D13: =B13-C13 -> 0 | E13: =SUMIFS(Savings!$D$4:$D$200,Savings!$B$4:$B$200,$A13,Savings!$F$4:$F$200,"Completed") -> 0 | F13: =SUMIFS(Loans!$H$4:$H$200,Loans!$G$4:$G$200,$A13,Loans!$I$4:$I$200,"Paid") -> 0 | G13: =Budget!$B$17 -> 740000 | H13: =G13-C13 -> 740000 | I13: =IFERROR(E13/B13,0) -> 0
A14: May 2027 | B14: =SUMIFS(Income!$F$4:$F$200,Income!$B$4:$B$200,$A14,Income!$G$4:$G$200,"Received") -> 0 | C14: =SUMIFS(Expenses!$F$4:$F$500,Expenses!$B$4:$B$500,$A14,Expenses!$H$4:$H$500,"Paid") -> 0 | D14: =B14-C14 -> 0 | E14: =SUMIFS(Savings!$D$4:$D$200,Savings!$B$4:$B$200,$A14,Savings!$F$4:$F$200,"Completed") -> 0 | F14: =SUMIFS(Loans!$H$4:$H$200,Loans!$G$4:$G$200,$A14,Loans!$I$4:$I$200,"Paid") -> 0 | G14: =Budget!$B$17 -> 740000 | H14: =G14-C14 -> 740000 | I14: =IFERROR(E14/B14,0) -> 0
A15: Jun 2027 | B15: =SUMIFS(Income!$F$4:$F$200,Income!$B$4:$B$200,$A15,Income!$G$4:$G$200,"Received") -> 0 | C15: =SUMIFS(Expenses!$F$4:$F$500,Expenses!$B$4:$B$500,$A15,Expenses!$H$4:$H$500,"Paid") -> 0 | D15: =B15-C15 -> 0 | E15: =SUMIFS(Savings!$D$4:$D$200,Savings!$B$4:$B$200,$A15,Savings!$F$4:$F$200,"Completed") -> 0 | F15: =SUMIFS(Loans!$H$4:$H$200,Loans!$G$4:$G$200,$A15,Loans!$I$4:$I$200,"Paid") -> 0 | G15: =Budget!$B$17 -> 740000 | H15: =G15-C15 -> 740000 | I15: =IFERROR(E15/B15,0) -> 0

Sheet Categories
A1: Income Sources | C1: Expense Categories | E1: Payment Methods | G1: Status | I1: Goal Status | K1: Months
A2: Salary | C2: Rent | E2: Bank Transfer | G2: Planned | I2: Not Started | K2: Jul 2026
A3: Commission | C3: Electricity/Security | E3: Cash | G3: Received | I3: In Progress | K3: Aug 2026
A4: Trading | C4: Internet/Airtime | E4: Card | G4: Paid | I4: Completed | K4: Sep 2026
A5: Business | C5: Transport | E5: POS | G5: Pending | I5: On Hold | K5: Oct 2026
A6: Gifts | C6: Food | E6: Mobile Money | G6: Completed | K6: Nov 2026
A7: Other | C7: Personal Care | E7: Direct Debit | G7: Overdue | K7: Dec 2026
C8: Healthcare | G8: Cancelled | K8: Jan 2027
C9: Family Support | K9: Feb 2027
C10: Church Giving | K10: Mar 2027
C11: Charity | K11: Apr 2027
C12: Education | K12: May 2027
C13: Travel | K13: Jun 2027
C14: Miscellaneous

Sheet README
A1: Personal Finance Tracker - User Guide
A3: Purpose | B3: This workbook helps you monitor income, expenses, savings, loans, budgets, and financial goals from July 2026 to June 2027.
A4: How to use | B4: 1. Update Income, Expenses, Savings, Loans, and Goals as transactions happen.
B5: 2. Review Budget to compare planned monthly spending with actual expenses.
B6: 3. Use Dashboard to select a month and review performance.
B7: 4. Use Monthly Summary to track trends across the financial year.
A8: Important note | B8: Cells with formulas should not be overwritten unless you want to customize the tracker.
A9: Currency | B9: NGN (₦)
A10: Financial Year | B10: July 2026 to June 2027
A11: Included Sheets | B11: Dashboard, Income, Expenses, Budget, Savings, Loans, Goals, Monthly Summary, Categories, README
A12: Portfolio Note | B12: This workbook can be uploaded as an Excel project under your portfolio with dashboard screenshots added later.
A14: Contact section | B14: Add your email, LinkedIn, and portfolio link on your portfolio page.
